leap_workflows/__init__.py
leap_workflows/api_client.py
leap_workflows/api_response.py
leap_workflows/apis/__init__.py
leap_workflows/apis/path_to_api.py
leap_workflows/apis/paths/__init__.py
leap_workflows/apis/paths/v1_runs.py
leap_workflows/apis/paths/v1_runs_bulk.py
leap_workflows/apis/paths/v1_runs_bulk_bulk_run_id.py
leap_workflows/apis/paths/v1_runs_workflow_run_id.py
leap_workflows/apis/tag_to_api.py
leap_workflows/apis/tags/__init__.py
leap_workflows/apis/tags/bulk_workflow_runs_api.py
leap_workflows/apis/tags/bulk_workflow_runs_api_raw.py
leap_workflows/apis/tags/workflow_runs_api.py
leap_workflows/apis/tags/workflow_runs_api_raw.py
leap_workflows/client.py
leap_workflows/client.pyi
leap_workflows/client_custom.py
leap_workflows/configuration.py
leap_workflows/exceptions.py
leap_workflows/exceptions_base.py
leap_workflows/model/__init__.py
leap_workflows/model/bulk_run_schema.py
leap_workflows/model/bulk_run_schema.pyi
leap_workflows/model/run_bulk_workflow_schema.py
leap_workflows/model/run_bulk_workflow_schema.pyi
leap_workflows/model/run_workflow_schema.py
leap_workflows/model/run_workflow_schema.pyi
leap_workflows/model/run_workflow_schema_input.py
leap_workflows/model/run_workflow_schema_input.pyi
leap_workflows/model/workflow_run_schema.py
leap_workflows/model/workflow_run_schema.pyi
leap_workflows/models/__init__.py
leap_workflows/operation_parameter_map.py
leap_workflows/paths/__init__.py
leap_workflows/paths/v1_runs/__init__.py
leap_workflows/paths/v1_runs/post.py
leap_workflows/paths/v1_runs/post.pyi
leap_workflows/paths/v1_runs_bulk/__init__.py
leap_workflows/paths/v1_runs_bulk/post.py
leap_workflows/paths/v1_runs_bulk/post.pyi
leap_workflows/paths/v1_runs_bulk_bulk_run_id/__init__.py
leap_workflows/paths/v1_runs_bulk_bulk_run_id/get.py
leap_workflows/paths/v1_runs_bulk_bulk_run_id/get.pyi
leap_workflows/paths/v1_runs_workflow_run_id/__init__.py
leap_workflows/paths/v1_runs_workflow_run_id/get.py
leap_workflows_python_sdk-2.0.3.dist-info/LICENSE
leap_workflows_python_sdk-2.0.3.dist-info/METADATA
leap_workflows_python_sdk-2.0.3.dist-info/WHEEL
leap_workflows_python_sdk-2.0.3.dist-info/RECORD
